tinybin/__init__.py
tinybin/index.html
tinybin-0.5.0.dist-info/METADATA
tinybin-0.5.0.dist-info/WHEEL
tinybin-0.5.0.dist-info/RECORD
